[
  {
    "id": "20ea214d9adc003d34bf319afcfe206ee062382768fcba43b445f98158a3e41e",
    "published_at": "2026-07-23T20:15:57+08:00",
    "timezone": "Asia/Taipei",
    "utc_offset": "+08:00",
    "taipei_date": "2026-07-23",
    "central_bank": "ECB",
    "headline": "ECB: In particular, ECB’s interest rate decisions will be based on its assessment of the inflation outlook and risks surrounding it, in light of incoming economic and financial data, as well as dynamics of underlying inflation",
    "source": "FinancialJuice",
    "fetched_at": "2026-07-23T20:50:58.152353+08:00"
  }
]
